Metadata-Version: 2.1
Name: noteql-jinjasql
Version: 0.1.10
Summary: Generate SQL Queries and Corresponding Bind Parameters using a Jinja2 Template
Home-page: https://github.com/kindly/noteql-jinjasql
Author: Sripathi Krishnan
Author-email: Sripathi.Krishnan@gmail.com
Maintainer: David Raznick
Maintainer-email: kindly@gmail.com
License: MIT
Keywords: Jinja2,SQL,Python,Template
Classifier: Development Status :: 4 - Beta
Classifier: Environment :: Console
Classifier: Intended Audience :: Developers
Classifier: License :: OSI Approved :: MIT License
Classifier: Operating System :: OS Independent
Classifier: Programming Language :: Python
Classifier: Programming Language :: Python :: 2.7
Classifier: Programming Language :: Python :: 3
Classifier: Programming Language :: Python :: 3.3
Classifier: Programming Language :: Python :: 3.4
Classifier: Programming Language :: Python :: 3.5
License-File: LICENSE
